LSS_dplona/LimitingSeaStates.py
LSS_dplona/__init__.py
LSS_dplona/utils/ExtractResults.py
LSS_dplona/utils/SeedsCreateVariations.py
LSS_dplona/utils/__init__.py
LSS_dplona/utils/multiProcess.py
LSS_dplona/utils/queueFolders.py
LSS_dplona-1.1.5.dist-info/LICENSE
LSS_dplona-1.1.5.dist-info/METADATA
LSS_dplona-1.1.5.dist-info/WHEEL
LSS_dplona-1.1.5.dist-info/top_level.txt
LSS_dplona-1.1.5.dist-info/RECORD
